{
  "schemaVersion": 1,
  "id": "billing",
  "title": "Billing",
  "description": "Plans, subscriptions, entitlement meters, usage, credits, and account activity.",
  "dependencies": ["data"],
  "endpoints": { "required": ["billing"], "optional": ["admin", "data"] },
  "capabilities": {
    "required": ["billing.plans", "billing.subscriptions"],
    "optional": ["billing.meters"]
  },
  "metadata": {
    "requiredMetaSections": ["tables", "fields", "constraints", "relations", "query"],
    "optionalMetaSections": ["scope", "encoding"],
    "requiredIntrospectionSections": ["root-operations", "types", "input-objects"],
    "optionalIntrospectionSections": ["enums", "directives"]
  }
}
